README.rst
run.py
setup.py
win_unicode_console/__init__.py
win_unicode_console/buffer.py
win_unicode_console/console.py
win_unicode_console/file_object.py
win_unicode_console/info.py
win_unicode_console/raw_input.py
win_unicode_console/readline_hook.py
win_unicode_console/runner.py
win_unicode_console/streams.py
win_unicode_console/tokenize_open.py
win_unicode_console/unicode_argv.py
win_unicode_console.egg-info/PKG-INFO
win_unicode_console.egg-info/SOURCES.txt
win_unicode_console.egg-info/dependency_links.txt
win_unicode_console.egg-info/top_level.txt