Metadata-Version: 1.1
Name: win_unicode_console
Version: 0.5
Summary: Enable Unicode input and display when running Python from Windows console.
Home-page: https://github.com/Drekin/win-unicode-console
Author: Drekin
Author-email: drekin@gmail.com
License: MIT
Download-URL: https://github.com/Drekin/win-unicode-console/archive/0.5.zip
Keywords: Windows,Unicode,console
Platform: UNKNOWN
Classifier: Development Status :: 4 - Beta
Classifier: Environment :: Console
Classifier: Intended Audience :: Developers
Classifier: License :: OSI Approved :: MIT License
Classifier: Operating System :: Microsoft :: Windows
Classifier: Programming Language :: Python :: 3
Classifier: Programming Language :: Python :: 3.4
Classifier: Programming Language :: Python :: 3.5
Classifier: Programming Language :: Python :: 2
Classifier: Programming Language :: Python :: 2.7
